opencovid19/__init__.py
opencovid19-0.0.1.dist-info/LICENSE
opencovid19-0.0.1.dist-info/WHEEL
opencovid19-0.0.1.dist-info/METADATA
opencovid19-0.0.1.dist-info/RECORD
